{
  "data": [
    [
      [
        1,
        null,
        0,
        0.0
      ],
      [
        -1173.201357347135,
        65.5638382434845,
        {
          "__enum__": "StatusType.SUCCESS"
        },
        1657127070.807428,
        1657127136.3933988,
        {}
      ]
    ],
    [
      [
        2,
        null,
        0,
        0.0
      ],
      [
        2147483647.0,
        30.280909299850464,
        {
          "__enum__": "StatusType.CRASHED"
        },
        1657127136.395105,
        1657127166.6763902,
        {}
      ]
    ],
    [
      [
        3,
        null,
        0,
        0.0
      ],
      [
        2147483647.0,
        0.15155982971191406,
        {
          "__enum__": "StatusType.CRASHED"
        },
        1657127166.7620249,
        1657127166.9463406,
        {}
      ]
    ],
    [
      [
        4,
        null,
        0,
        0.0
      ],
      [
        2147483647.0,
        0.6661858558654785,
        {
          "__enum__": "StatusType.CRASHED"
        },
        1657127167.0153387,
        1657127167.7108881,
        {}
      ]
    ],
    [
      [
        5,
        null,
        0,
        0.0
      ],
      [
        2147483647.0,
        0.4771728515625,
        {
          "__enum__": "StatusType.CRASHED"
        },
        1657127167.8284686,
        1657127168.332855,
        {}
      ]
    ]
  ],
  "config_origins": {
    "1": "Sobol",
    "2": "Sobol",
    "3": "Local Search",
    "4": "Local Search",
    "5": "Local Search"
  },
  "configs": {
    "1": {
      "dt": false,
      "g": false,
      "l": true,
      "m": false,
      "max_speed": true
    },
    "2": {
      "dt": true,
      "g": true,
      "l": false,
      "m": true,
      "max_speed": false
    },
    "3": {
      "dt": true,
      "g": false,
      "l": true,
      "m": false,
      "max_speed": true
    },
    "4": {
      "dt": false,
      "g": false,
      "l": true,
      "m": false,
      "max_speed": false
    },
    "5": {
      "dt": false,
      "g": false,
      "l": true,
      "m": true,
      "max_speed": true
    }
  }
}